robokassa/__init__.py
robokassa/client.py
robokassa/connection.py
robokassa/exceptions.py
robokassa/hash.py
robokassa/jwt.py
robokassa/merchant.py
robokassa/payment.py
robokassa/signature.py
robokassa/types.py
robokassa-1.0.8.dist-info/METADATA
robokassa-1.0.8.dist-info/WHEEL
robokassa-1.0.8.dist-info/licenses/LICENSE
robokassa-1.0.8.dist-info/RECORD
