Metadata-Version: 2.4
Name: robokassa
Version: 1.0.8
Summary: Unofficial Robokassa API
License-File: LICENSE
Author: Ben Puls
Author-email: mail@benpuls.ru
Requires-Python: >=3.8
Classifier: Programming Language :: Python :: 3
Classifier: Programming Language :: Python :: 3.8
Classifier: Programming Language :: Python :: 3.9
Classifier: Programming Language :: Python :: 3.10
Classifier: Programming Language :: Python :: 3.11
Classifier: Programming Language :: Python :: 3.12
Classifier: Programming Language :: Python :: 3.13
Classifier: Programming Language :: Python :: 3.14
Requires-Dist: httpx (>=0.27.2)
Project-URL: Documentation, https://robokassa.readthedocs.io/
Project-URL: Homepage, https://github.com/byBenPuls/robokassa
Project-URL: Repository, https://github.com/byBenPuls/robokassa
